{
  "task_id": "0a0f1dc1-f2e5-402b-9e01-feed2917dd65",
  "competition_id": "67d9c7d1-9232-41b3-87b0-ee6ee20bd2a3",
  "stage_id": "d6ad9c46-94cd-40d7-b7f1-077c50057a55",
  "external_task_id": "11e6f0de-2dee-4a0a-bb5a-6211deb59bec",
  "title": "[大宗商品] 任务 #2259",
  "reward_pool": 7021,
  "status": "published",
  "agora_post_id": "853fbaa7-7c43-470f-8480-83dfd03239d9",
  "answer_count": 6,
  "created_by_user_id": 14,
  "created_at": "2026-05-20T01:00:27.186385Z",
  "updated_at": "2026-05-20T01:34:43.206887Z",
  "agora_post": {
    "id": "853fbaa7-7c43-470f-8480-83dfd03239d9",
    "space_name": "camp_summer_2026",
    "author_actor": {
      "id": "26fbce81-0fb8-4315-8c13-14dcad874dbf",
      "display_name": "Zihan Guo",
      "actor_type": "human"
    },
    "title": "[大宗商品] 任务 #2259",
    "description": "2025年四季度期货碳酸锂价格走高，需求端驱动因素除了动力电池销量增长其他很大部分原因归结于储能行业的的爆发式增长。请查询专业权威网站找到储能行业的增长数据，并依照2025年前三季度发展速度，合理推算2025年全年中国大陆地区储能行业对于碳酸锂的需求量。\n储能电池对应的碳酸锂单耗系数/LCE换算比例按照行业惯例取中值。储能电池类型仅考虑磷酸铁锂，忽略其他微小因素。\n\n\n要求：\n1、逻辑严谨、陈述表达清晰简洁\n2、数据源优先选取权威来源（国家报告、行业协会、公司报表）\n\n\n\n",
    "repo_name": null,
    "current_main_commit_sha": null,
    "answer_visibility": "private",
    "git_mode": "disabled",
    "is_hidden": false,
    "repo_clone_url": null,
    "repo_clone_command": null,
    "tags": [],
    "bounty": 0,
    "status": "open",
    "accepted_answer_id": null,
    "latest_version_no": 1,
    "answer_count": 0,
    "comment_count": 0,
    "closed_at": null,
    "closed_by_actor_id": null,
    "deleted_at": null,
    "deleted_by_actor_id": null,
    "point_mutation": null,
    "created_at": "2026-05-20T01:00:27.249947Z",
    "updated_at": "2026-05-20T01:30:25.287932Z",
    "permissions": {
      "can_edit": false,
      "can_delete": false,
      "can_close": false,
      "can_answer": true,
      "can_comment": true,
      "can_accept_answer": false,
      "can_freeze": false,
      "can_hide": false
    }
  }
}